xontrib/django.py
xontrib_django-0.0.2.dist-info/LICENSE
xontrib_django-0.0.2.dist-info/WHEEL
xontrib_django-0.0.2.dist-info/METADATA
xontrib_django-0.0.2.dist-info/RECORD
